moduels/seven_seg2.vhd
library ieee;
use ieee.std_logic_1164.all;
use ieee.numeric_std.all;

entity two_seven_seg is
    port(
        d: in unsigned(3 downto 0);            
        first_part: out std_logic_vector(6 downto 0); 
        second_part: out std_logic_vector(6 downto 0)  
    );
end two_seven_seg;

architecture behavioral of two_seven_seg is
begin
    first_part <= 
        "0000110" when d >= "1010" else
        "0111111";
    second_part <=
        "0111111" when d = "0000" else
        "0000110" when d = "0001" else
        "1011011" when d = "0010" else
        "1001111" when d = "0011" else
        "1100110" when d = "0100" else
        "1101101" when d = "0101" else
        "1111101" when d = "0110" else
        "0000111" when d = "0111" else
        "1111111" when d = "1000" else
        "1101111" when d = "1001" else
        "0111111" when d = "1010" else
        "0000110" when d = "1011" else
        "1011011" when d = "1100" else
        "0000000";    

end behavioral;

testbenches/tb_seven_seg2.vhd
library ieee;
use ieee.std_logic_1164.all;
use ieee.numeric_std.all;

entity tb_two_seven_seg is
end tb_two_seven_seg;

architecture sim of tb_two_seven_seg is
    signal d: unsigned(3 downto 0) := "0000";
    signal first_part, second_part: std_logic_vector(6 downto 0);
begin

    -- Unit Under Test
    uut: entity work.two_seven_seg
        port map(
            d => d,
            first_part => first_part,
            second_part => second_part
        );
    d <= "0000" after 0 ns,
         "0001" after 10 ns,
         "0010" after 20 ns,
         "0011" after 30 ns,
         "0100" after 40 ns,
         "0101" after 50 ns,
         "0110" after 60 ns,
         "0111" after 70 ns,
         "1000" after 80 ns,
         "1001" after 90 ns,
         "1010" after 100 ns,
         "1011" after 110 ns,
         "1100" after 120 ns, 
         "0000" after 140 ns;

end sim;

work/tb_seven_seg2.vcd
$date
  Mon Feb  9 23:04:13 2026
$end
$version
  GHDL v0
$end
$timescale
  1 fs
$end
$scope module standard $end
$upscope $end
$scope module std_logic_1164 $end
$upscope $end
$scope module numeric_std $end
$upscope $end
$scope module tb_two_seven_seg $end
$var reg 4 ! d[3:0] $end
$var reg 7 " first_part[6:0] $end
$var reg 7 # second_part[6:0] $end
$scope module uut $end
$var reg 4 $ d[3:0] $end
$var reg 7 % first_part[6:0] $end
$var reg 7 & second_part[6:0] $end
$upscope $end
$upscope $end
$enddefinitions $end
#0
b0000 !
b0111111 "
b0111111 #
b0000 $
b0111111 %
b0111111 &
#10000000
b0001 !
b0000110 #
b0001 $
b0000110 &
#20000000
b0010 !
b1011011 #
b0010 $
b1011011 &
#30000000
b0011 !
b1001111 #
b0011 $
b1001111 &
#40000000
b0100 !
b1100110 #
b0100 $
b1100110 &
#50000000
b0101 !
b1101101 #
b0101 $
b1101101 &
#60000000
b0110 !
b1111101 #
b0110 $
b1111101 &
#70000000
b0111 !
b0000111 #
b0111 $
b0000111 &
#80000000
b1000 !
b1111111 #
b1000 $
b1111111 &
#90000000
b1001 !
b1101111 #
b1001 $
b1101111 &
#100000000
b1010 !
b0000110 "
b0111111 #
b1010 $
b0000110 %
b0111111 &
#110000000
b1011 !
b0000110 #
b1011 $
b0000110 &
#120000000
b1100 !
b1011011 #
b1100 $
b1011011 &
#140000000
b0000 !
b0111111 "
b0111111 #
b0000 $
b0111111 %
b0111111 &
